MANIFEST.in
setup.cfg
setup.py
csembedlyparser/CHANGES.txt
csembedlyparser/__init__.py
csembedlyparser/admin.py
csembedlyparser/models.py
csembedlyparser.egg-info/PKG-INFO
csembedlyparser.egg-info/SOURCES.txt
csembedlyparser.egg-info/dependency_links.txt
csembedlyparser.egg-info/not-zip-safe
csembedlyparser.egg-info/requires.txt
csembedlyparser.egg-info/top_level.txt
csembedlyparser/migrations/0001_initial.py
csembedlyparser/migrations/0002_alter_embedlyparsed_title_and_more.py
csembedlyparser/migrations/__init__.py
csembedlyparser/templates/csembedlyparser/big.html
csembedlyparser/templates/csembedlyparser/big_base.html
csembedlyparser/templates/csembedlyparser/big_oembed_link.html
csembedlyparser/templates/csembedlyparser/big_oembed_photo.html
csembedlyparser/templates/csembedlyparser/big_oembed_rich.html
csembedlyparser/templates/csembedlyparser/big_oembed_video.html
csembedlyparser/templates/csembedlyparser/default.html
csembedlyparser/templates/csembedlyparser/medium.html
csembedlyparser/templates/csembedlyparser/medium_base.html
csembedlyparser/templates/csembedlyparser/medium_oembed_link.html
csembedlyparser/templates/csembedlyparser/medium_oembed_photo.html
csembedlyparser/templates/csembedlyparser/medium_oembed_rich.html
csembedlyparser/templates/csembedlyparser/medium_oembed_video.html
csembedlyparser/utils/__init__.py
csembedlyparser/utils/chars.py
csembedlyparser/utils/datetime_utils.py
csembedlyparser/utils/slug.py