Metadata-Version: 2.1
Name: csembedlyparser
Version: 2.3
Home-page: 
Author: 
Author-email: 
Requires-Dist: httplib2
Requires-Dist: embedly2
